invenio_formatter/__init__.py
invenio_formatter/config.py
invenio_formatter/ext.py
invenio_formatter/views.py
invenio_formatter/context_processors/__init__.py
invenio_formatter/context_processors/badges.py
invenio_formatter/filters/__init__.py
invenio_formatter/filters/datetime.py
invenio_formatter/filters/html.py
invenio_formatter/templates/invenio_formatter/macros/badges.html
invenio_formatter/templates/invenio_formatter/macros/meta.html
invenio_formatter/templates/semantic-ui/invenio_formatter/macros/badges.html
invenio_formatter/templates/semantic-ui/invenio_formatter/macros/meta.html
invenio_formatter/translations/messages.pot
invenio_formatter/translations/ar/LC_MESSAGES/messages.mo
invenio_formatter/translations/ar/LC_MESSAGES/messages.po
invenio_formatter/translations/bg/LC_MESSAGES/messages.mo
invenio_formatter/translations/bg/LC_MESSAGES/messages.po
invenio_formatter/translations/ca/LC_MESSAGES/messages.mo
invenio_formatter/translations/ca/LC_MESSAGES/messages.po
invenio_formatter/translations/cs/LC_MESSAGES/messages.mo
invenio_formatter/translations/cs/LC_MESSAGES/messages.po
invenio_formatter/translations/da/LC_MESSAGES/messages.mo
invenio_formatter/translations/da/LC_MESSAGES/messages.po
invenio_formatter/translations/de/LC_MESSAGES/messages.mo
invenio_formatter/translations/de/LC_MESSAGES/messages.po
invenio_formatter/translations/el/LC_MESSAGES/messages.mo
invenio_formatter/translations/el/LC_MESSAGES/messages.po
invenio_formatter/translations/en/LC_MESSAGES/messages.mo
invenio_formatter/translations/en/LC_MESSAGES/messages.po
invenio_formatter/translations/es/LC_MESSAGES/messages.mo
invenio_formatter/translations/es/LC_MESSAGES/messages.po
invenio_formatter/translations/et/LC_MESSAGES/messages.mo
invenio_formatter/translations/et/LC_MESSAGES/messages.po
invenio_formatter/translations/fa/LC_MESSAGES/messages.mo
invenio_formatter/translations/fa/LC_MESSAGES/messages.po
invenio_formatter/translations/fi/LC_MESSAGES/messages.mo
invenio_formatter-3.3.1.dist-info/licenses/AUTHORS.rst
invenio_formatter-3.3.1.dist-info/licenses/LICENSE
invenio_formatter-3.3.1.dist-info/METADATA
invenio_formatter-3.3.1.dist-info/WHEEL
invenio_formatter-3.3.1.dist-info/entry_points.txt
invenio_formatter-3.3.1.dist-info/top_level.txt
invenio_formatter-3.3.1.dist-info/RECORD
