Metadata-Version: 2.4
Name: invenio-formatter
Version: 3.3.1
Summary: "Jinja utilities for Invenio."
Home-page: https://github.com/inveniosoftware/invenio-formatter
Author: CERN
Author-email: info@inveniosoftware.org
License: MIT
Keywords: invenio jinja2 flask
Platform: any
Classifier: Development Status :: 3 - Alpha
Requires-Python: >=3.8
License-File: LICENSE
License-File: AUTHORS.rst
Requires-Dist: arrow>=0.7.0
Requires-Dist: bleach>=3.1.0
Requires-Dist: invenio-base<3.0.0,>=2.0.0
Requires-Dist: invenio-i18n<4.0.0,>=3.0.0
Requires-Dist: Pillow>=10.0.0
Provides-Extra: tests
Requires-Dist: pytest-black-ng>=0.4.0; extra == "tests"
Requires-Dist: pytest-invenio<4.0.0,>=3.0.0; extra == "tests"
Requires-Dist: mock>=4.0.3; extra == "tests"
Requires-Dist: Sphinx>=1.8.0; extra == "tests"
Requires-Dist: CairoSVG>=1.0.20; extra == "tests"
Requires-Dist: Pillow>=10.0.0; extra == "tests"
Dynamic: license-file
